LICENSE
README.md
setup.py
frida_devices_manager/__init__.py
frida_devices_manager/constants.py
frida_devices_manager/core.py
frida_devices_manager.egg-info/PKG-INFO
frida_devices_manager.egg-info/SOURCES.txt
frida_devices_manager.egg-info/dependency_links.txt
frida_devices_manager.egg-info/top_level.txt
tests/test_core.py